mssql_mcp_server/__init__.py
mssql_mcp_server/server.py
mssql_mcp_server-0.1.2.dist-info/METADATA
mssql_mcp_server-0.1.2.dist-info/WHEEL
mssql_mcp_server-0.1.2.dist-info/entry_points.txt
mssql_mcp_server-0.1.2.dist-info/licenses/LICENSE
mssql_mcp_server-0.1.2.dist-info/RECORD
