Metadata-Version: 2.4
Name: mssql_mcp_server
Version: 0.1.2
Summary: A Model Context Protocol (MCP) server that enables secure interaction with MSSQL databases. This server allows AI assistants to list tables, read data, and execute SQL queries through a controlled interface, making database exploration and analysis safer and more structured.
Author-email: Jexin Sam <jexin.sam@gmail.com>
License-File: LICENSE
Requires-Python: >=3.11
Requires-Dist: httpx>=0.28.1
Requires-Dist: mcp[cli]>=1.0.0
Requires-Dist: pyodbc>=5.2.0
